nagel.py
nagel-0.0.1.dist-info/LICENSE
nagel-0.0.1.dist-info/WHEEL
nagel-0.0.1.dist-info/METADATA
nagel-0.0.1.dist-info/RECORD
