Metadata-Version: 2.1
Name: nagel
Version: 0.0.1
Summary: Straightforward pastebin software.
Home-page: https://github.com/supakeen/nagel
License: MIT
Keywords: pastebin
Author: supakeen
Author-email: cmdr@supakeen.com
Requires-Python: >=3.6,<4
Classifier: License :: OSI Approved :: MIT License
Classifier: Programming Language :: Python
Classifier: Programming Language :: Python :: 3
Classifier: Programming Language :: Python :: 3.6
Classifier: Programming Language :: Python :: 3.7
Classifier: Programming Language :: Python :: 3.8
Requires-Dist: requests (>=2.23.0,<3.0.0)
Project-URL: Repository, https://github.com/supakeen/nagel
